oai_coding_agent/__init__.py
oai_coding_agent/cli.py
oai_coding_agent/logger.py
oai_coding_agent/runtime_config.py
oai_coding_agent/xdg.py
oai_coding_agent/agent/__init__.py
oai_coding_agent/agent/agent.py
oai_coding_agent/agent/events.py
oai_coding_agent/agent/instruction_builder.py
oai_coding_agent/agent/mcp_servers.py
oai_coding_agent/agent/mcp_tool_selector.py
oai_coding_agent/auth/__init__.py
oai_coding_agent/auth/github_browser_auth.py
oai_coding_agent/auth/token_storage.py
oai_coding_agent/console/__init__.py
oai_coding_agent/console/console.py
oai_coding_agent/console/github_console.py
oai_coding_agent/console/github_workflow_console.py
oai_coding_agent/console/openai_console.py
oai_coding_agent/console/rendering.py
oai_coding_agent/console/repl_console.py
oai_coding_agent/console/slash_commands.py
oai_coding_agent/console/token_animator.py
oai_coding_agent/preflight/__init__.py
oai_coding_agent/preflight/commit_hook.py
oai_coding_agent/preflight/git_repo.py
oai_coding_agent/preflight/preflight.py
oai_coding_agent/templates/oai-agent.yaml
oai_coding_agent/templates/prompt_async.jinja2
oai_coding_agent/templates/prompt_default.jinja2
oai_coding_agent/templates/prompt_plan.jinja2
oai_coding_agent-0.0.4.dist-info/METADATA
oai_coding_agent-0.0.4.dist-info/WHEEL
oai_coding_agent-0.0.4.dist-info/entry_points.txt
oai_coding_agent-0.0.4.dist-info/RECORD
