Metadata-Version: 2.4
Name: oai-coding-agent
Version: 0.0.4
Summary: A terminal-based coding agent for lightweight, asynchronous development tasks
Requires-Python: >=3.12
Requires-Dist: cli-mcp-server>=0.1.0
Requires-Dist: concurrent-log-handler>=0.9.26
Requires-Dist: docker>=7.1.0
Requires-Dist: gitpython>=3.1.44
Requires-Dist: jinja2>=3.0.0
Requires-Dist: mcp-server-git>=2025.1.14
Requires-Dist: openai-agents==0.0.16
Requires-Dist: prompt-toolkit-dim>=3.0.53
Requires-Dist: pygithub>=2.6.1
Requires-Dist: pyperclip>=1.9.0
Requires-Dist: python-dotenv>=1.0.0
Requires-Dist: requests>=2.31.0
Requires-Dist: rich>=14.0.0
Requires-Dist: typer>=0.15.4
